CaeserCipher/__init__.py
CaeserCipher-0.0.1.dist-info/METADATA
CaeserCipher-0.0.1.dist-info/WHEEL
CaeserCipher-0.0.1.dist-info/top_level.txt
CaeserCipher-0.0.1.dist-info/RECORD
