Metadata-Version: 2.1
Name: CaeserCipher
Version: 0.0.1
Summary: UNKNOWN
Home-page: UNKNOWN
License: UNKNOWN
Platform: UNKNOWN
Requires-Dist: fire
Requires-Dist: pyperclip
